sampiclyser/__init__.py
sampiclyser/entry_points.py
sampiclyser/sampic_convert_script.py
sampiclyser/sampic_decoder.py
sampiclyser/sampic_tools.py
sampiclyser/sensor_hitmaps.py
sampiclyser/utility_entry_points.py
sampiclyser-0.1.2.dist-info/METADATA
sampiclyser-0.1.2.dist-info/WHEEL
sampiclyser-0.1.2.dist-info/entry_points.txt
sampiclyser-0.1.2.dist-info/licenses/AUTHORS.rst
sampiclyser-0.1.2.dist-info/licenses/LICENSE
sampiclyser-0.1.2.dist-info/RECORD
